odoo/addons/board_eval_context/README.rst
odoo/addons/board_eval_context/__init__.py
odoo/addons/board_eval_context/__manifest__.py
odoo/addons/board_eval_context/i18n/board_eval_context.pot
odoo/addons/board_eval_context/i18n/es.po
odoo/addons/board_eval_context/models/__init__.py
odoo/addons/board_eval_context/models/board_board.py
odoo/addons/board_eval_context/readme/DESCRIPTION.rst
odoo/addons/board_eval_context/static/description/icon.png
odoo/addons/board_eval_context/static/description/index.html
odoo_addon_board_eval_context-15.0.1.0.0.6.dist-info/METADATA
odoo_addon_board_eval_context-15.0.1.0.0.6.dist-info/WHEEL
odoo_addon_board_eval_context-15.0.1.0.0.6.dist-info/top_level.txt
odoo_addon_board_eval_context-15.0.1.0.0.6.dist-info/RECORD
